pepBridge/MALDI_LCMS.py
pepBridge/MatchingMZ.py
pepBridge/__init__.py
pepBridge/config_file.py
pepBridge/bin/__init__.py
pepBridge/bin/copy_data.py
pepBridge/bin/pepbridge.py
pepBridge/class_diagrams/pepBridge_class_diagram-1.png
pepBridge/config_files/lcms.ini
pepBridge/config_files/maldi.ini
pepBridge/data/IMS199_OTD196_GK_Thymus_ChemoL_v_CtrlR_MALDI_Match_LCMS_wTrypsinR05_4K_Oct2024_LCMS.csv
pepBridge/data/IMS199_OTD196_GK_Thymus_ChemoL_v_CtrlR_MALDI_Match_LCMS_wTrypsinR05_4K_Oct2024_MALDI.csv
pepBridge-1.0.41.dist-info/LICENSE-GPL-3.0
pepBridge-1.0.41.dist-info/METADATA
pepBridge-1.0.41.dist-info/WHEEL
pepBridge-1.0.41.dist-info/entry_points.txt
pepBridge-1.0.41.dist-info/top_level.txt
pepBridge-1.0.41.dist-info/RECORD
